pyqt4topyqt5_pkg/__init__.py
pyqt4topyqt5_pkg/pyqt4topyqt5.py
pyqt4topyqt5_pkg/qtclass.py
pyqt4topyqt5-1.0.0.dist-info/LICENSE
pyqt4topyqt5-1.0.0.dist-info/METADATA
pyqt4topyqt5-1.0.0.dist-info/WHEEL
pyqt4topyqt5-1.0.0.dist-info/top_level.txt
pyqt4topyqt5-1.0.0.dist-info/RECORD
