Metadata-Version: 2.1
Name: pyqt4topyqt5
Version: 1.0.0
Summary: pyqt4 -> pyqt5
Home-page: https://github.com/rferrazz/pyqt4topyqt5/
Author: rferrazz
License: UNKNOWN
Platform: UNKNOWN
Classifier: Programming Language :: Python :: 3
Classifier: License :: OSI Approved :: GNU Lesser General Public License v3 (LGPLv3)
Classifier: Operating System :: OS Independent
Requires-Python: >=3.6
